pydantic_remote_config/__init__.py
pydantic_remote_config/aws/__init__.py
pydantic_remote_config/aws/client.py
pydantic_remote_config/aws/secrets_manager.py
pydantic_remote_config/aws/ssm.py
pydantic_remote_config/config/__init__.py
pydantic_remote_config/config/aws.py
pydantic_remote_config/enum/VendorName.py
pydantic_remote_config/enum/__init__.py
pydantic_remote_config/exceptions.py
pydantic_remote_config/pydantic.py
pydantic_remote_config-0.1.0.dist-info/LICENSE
pydantic_remote_config-0.1.0.dist-info/WHEEL
pydantic_remote_config-0.1.0.dist-info/METADATA
pydantic_remote_config-0.1.0.dist-info/RECORD
